{"getQuotesResponse":[

{
  "pricerId": "72514",
  "rank": "67089",
  "programCode": "ARC", Program
  "programText": "Absolute Reserve Car Plus",
  "coverage": "Exclusionary", Coverage
  "classRoom": "2",
  "term": "60/100", Term/Miles	
  "planMonths": "60",
  "planMiles": "100000",
  "price": "931.0000",
  "awd": "",All Wheel Drive(AWD)?	
  "turbo": "",
  "diesel": "",
  "hv": "",
  "buse": "250.0000",
  "sg": "0.0000",
  "wr": "",
  "dd": "100.0000",
  "deductible_0": "", Deductable
  "deductible_50": "",
  "deductible_100": "0.0000",
  "deductible_250": "-85.0000"
},

{"pricerId":"73486","rank":"67089","programCode":"ARC","programText":"Absolute Reserve Car Plus","coverage":"Exclusionary","classRoom":"2",
"term":"72/100","planMonths":"72","planMiles":"100000","price":"1146.0000","awd":"","turbo":"","diesel":"","hv":"","buse":"250.0000",
"sg":"0.0000","wr":"","dd":"100.0000","deductible_0":"","deductible_50":"","deductible_100":"0.0000","deductible_250":"-125.0000"},

{"pricerId":"73558","rank":"67089","programCode":"ARC","programText":"Absolute Reserve Car Plus","coverage":"Exclusionary","classRoom":"2",
"term":"72/125","planMonths":"72","planMiles":"125000","price":"1367.0000","awd":"","turbo":"","diesel":"","hv":"","buse":"250.0000",
"sg":"0.0000","wr":"","dd":"100.0000","deductible_0":"","deductible_50":"","deductible_100":"0.0000","deductible_250":"-125.0000"},

{"pricerId":"141704","rank":"141701","programCode":"NSC","programText":"New Vehicle - NSC","coverage":"RESERVE","classRoom":"4",
"term":"48/60","planMonths":"48","planMiles":"60000","price":"908.0000","awd":"","turbo":"","diesel":"","hv":"","buse":"250.0000",
"sg":"","wr":"","dd":"50.0000","deductible_0":"200.0000","deductible_50":"100.0000","deductible_100":"0.0000","deductible_250":""},

{"pricerId":"141722","rank":"141701","programCode":"NSC","programText":"New Vehicle - NSC","coverage":"RESERVE","classRoom":"4",
"term":"48/75","planMonths":"48","planMiles":"75000","price":"1040.0000","awd":"","turbo":"","diesel":"","hv":"","buse":"250.0000",
"sg":"","wr":"","dd":"50.0000","deductible_0":"200.0000","deductible_50":"100.0000","deductible_100":"0.0000","deductible_250":""},

{"pricerId":"141740","rank":"141701","programCode":"NSC","programText":"New Vehicle - NSC","coverage":"RESERVE","classRoom":"4",
"term":"48/100","planMonths":"48","planMiles":"100000","price":"1164.0000","awd":"","turbo":"","diesel":"","hv":"","buse":"250.0000",
"sg":"","wr":"","dd":"50.0000","deductible_0":"200.0000","deductible_50":"100.0000","deductible_100":"0.0000","deductible_250":""},

{"pricerId":"141758","rank":"141701","programCode":"NSC","programText":"New Vehicle - NSC","coverage":"RESERVE","classRoom":"4",
"term":"60/60","planMonths":"60","planMiles":"60000","price":"981.0000","awd":"","turbo":"","diesel":"","hv":"","buse":"250.0000",
"sg":"","wr":"","dd":"50.0000","deductible_0":"200.0000","deductible_50":"100.0000","deductible_100":"0.0000","deductible_250":""},

{"pricerId":"141776","rank":"141701","programCode":"NSC","programText":"New Vehicle - NSC","coverage":"RESERVE","classRoom":"4",
"term":"60/75","planMonths":"60","planMiles":"75000","price":"1064.0000","awd":"","turbo":"","diesel":"","hv":"","buse":"250.0000",
"sg":"","wr":"","dd":"50.0000","deductible_0":"200.0000","deductible_50":"100.0000","deductible_100":"0.0000","deductible_250":""},

{"pricerId":"141794","rank":"141701","programCode":"NSC","programText":"New Vehicle - NSC","coverage":"RESERVE","classRoom":"4",
"term":"60/100","planMonths":"60","planMiles":"100000","price":"1175.0000","awd":"","turbo":"","diesel":"","hv":"","buse":"250.0000",
"sg":"","wr":"","dd":"50.0000","deductible_0":"200.0000","deductible_50":"100.0000","deductible_100":"0.0000","deductible_250":""},

{"pricerId":"141812","rank":"141701","programCode":"NSC","programText":"New Vehicle - NSC","coverage":"RESERVE","classRoom":"4",
"term":"72/60","planMonths":"72","planMiles":"60000","price":"1077.0000","awd":"","turbo":"","diesel":"","hv":"","buse":"250.0000",
"sg":"","wr":"","dd":"50.0000","deductible_0":"200.0000","deductible_50":"100.0000","deductible_100":"0.0000","deductible_250":""},

{"pricerId":"141830","rank":"141701","programCode":"NSC","programText":"New Vehicle - NSC","coverage":"RESERVE","classRoom":"4",
"term":"72/75","planMonths":"72","planMiles":"75000","price":"1089.0000","awd":"","turbo":"","diesel":"","hv":"","buse":"250.0000",
"sg":"","wr":"","dd":"50.0000","deductible_0":"200.0000","deductible_50":"100.0000","deductible_100":"0.0000","deductible_250":""},

{"pricerId":"141848","rank":"141701","programCode":"NSC","programText":"New Vehicle - NSC","coverage":"RESERVE","classRoom":"4",
"term":"72/100","planMonths":"72","planMiles":"100000","price":"1208.0000","awd":"","turbo":"","diesel":"","hv":"","buse":"250.0000",
"sg":"","wr":"","dd":"50.0000","deductible_0":"200.0000","deductible_50":"100.0000","deductible_100":"0.0000","deductible_250":""},

{"pricerId":"141866","rank":"141863","programCode":"NSC","programText":"New Vehicle - NSC","coverage":"WRAP","classRoom":"4",
"term":"60/60","planMonths":"60","planMiles":"60000","price":"843.0000","awd":"","turbo":"","diesel":"","hv":"","buse":"250.0000",
"sg":"","wr":"","dd":"50.0000","deductible_0":"200.0000","deductible_50":"100.0000","deductible_100":"0.0000","deductible_250":""},

{"pricerId":"141884","rank":"141863","programCode":"NSC","programText":"New Vehicle - NSC","coverage":"WRAP","classRoom":"4",
"term":"60/100","planMonths":"60","planMiles":"100000","price":"1054.0000","awd":"","turbo":"","diesel":"","hv":"","buse":"250.0000",
"sg":"","wr":"","dd":"50.0000","deductible_0":"200.0000","deductible_50":"100.0000","deductible_100":"0.0000","deductible_250":""},

{"pricerId":"141902","rank":"141863","programCode":"NSC","programText":"New Vehicle - NSC","coverage":"WRAP","classRoom":"4",
"term":"72/70","planMonths":"72","planMiles":"70000","price":"962.0000","awd":"","turbo":"","diesel":"","hv":"","buse":"250.0000",
"sg":"","wr":"","dd":"50.0000","deductible_0":"200.0000","deductible_50":"100.0000","deductible_100":"0.0000","deductible_250":""},

{"pricerId":"141920","rank":"141863","programCode":"NSC","programText":"New Vehicle - NSC","coverage":"WRAP","classRoom":"4",
"term":"72/75","planMonths":"72","planMiles":"75000","price":"997.0000","awd":"","turbo":"","diesel":"","hv":"","buse":"250.0000",
"sg":"","wr":"","dd":"50.0000","deductible_0":"200.0000","deductible_50":"100.0000","deductible_100":"0.0000","deductible_250":""},

{"pricerId":"141938","rank":"141863","programCode":"NSC","programText":"New Vehicle - NSC","coverage":"WRAP","classRoom":"4",
"term":"72/100","planMonths":"72","planMiles":"100000","price":"1125.0000","awd":"","turbo":"","diesel":"","hv":"","buse":"250.0000",
"sg":"","wr":"","dd":"50.0000","deductible_0":"200.0000","deductible_50":"100.0000","deductible_100":"0.0000","deductible_250":""},

{"pricerId":"141956","rank":"141863","programCode":"NSC","programText":"New Vehicle - NSC","coverage":"WRAP","classRoom":"4",
"term":"84/70","planMonths":"84","planMiles":"70000","price":"1017.0000","awd":"","turbo":"","diesel":"","hv":"","buse":"250.0000",
"sg":"","wr":"","dd":"50.0000","deductible_0":"200.0000","deductible_50":"100.0000","deductible_100":"0.0000","deductible_250":""},

{"pricerId":"141974","rank":"141863","programCode":"NSC","programText":"New Vehicle - NSC","coverage":"WRAP","classRoom":"4",
"term":"84/100","planMonths":"84","planMiles":"100000","price":"1196.0000","awd":"","turbo":"","diesel":"","hv":"","buse":"250.0000",
"sg":"","wr":"","dd":"50.0000","deductible_0":"200.0000","deductible_50":"100.0000","deductible_100":"0.0000","deductible_250":""},

{"pricerId":"141992","rank":"141863","programCode":"NSC","programText":"New Vehicle - NSC","coverage":"WRAP","classRoom":"4",
"term":"120/100","planMonths":"120","planMiles":"100000","price":"1325.0000","awd":"","turbo":"","diesel":"","hv":"","buse":"250.0000",
"sg":"","wr":"","dd":"50.0000","deductible_0":"200.0000","deductible_50":"100.0000","deductible_100":"0.0000","deductible_250":""},

{"pricerId":"655451","rank":"655448","programCode":"NSE","programText":"New Vehicle - NSE","coverage":"Reserve","classRoom":"4",
"term":"48/60","planMonths":"48","planMiles":"60000","price":"908.0000","awd":"","turbo":"","diesel":"","hv":"","buse":"250.0000",
"sg":"","wr":"","dd":"50.0000","deductible_0":"200.0000","deductible_50":"100.0000","deductible_100":"0.0000","deductible_250":""},

{"pricerId":"655457","rank":"655448","programCode":"NSE","programText":"New Vehicle - NSE","coverage":"Reserve","classRoom":"4",
"term":"48/75","planMonths":"48","planMiles":"75000","price":"1054.0000","awd":"","turbo":"","diesel":"","hv":"","buse":"250.0000",
"sg":"","wr":"","dd":"50.0000","deductible_0":"200.0000","deductible_50":"100.0000","deductible_100":"0.0000","deductible_250":""},

{"pricerId":"655463","rank":"655448","programCode":"NSE","programText":"New Vehicle - NSE","coverage":"Reserve","classRoom":"4",
"term":"48/100","planMonths":"48","planMiles":"100000","price":"1170.0000","awd":"","turbo":"","diesel":"","hv":"","buse":"250.0000",
"sg":"","wr":"","dd":"50.0000","deductible_0":"200.0000","deductible_50":"100.0000","deductible_100":"0.0000","deductible_250":""},

{"pricerId":"655469","rank":"655448","programCode":"NSE","programText":"New Vehicle - NSE","coverage":"Reserve","classRoom":"4",
"term":"60/60","planMonths":"60","planMiles":"60000","price":"994.0000","awd":"","turbo":"","diesel":"","hv":"","buse":"250.0000",
"sg":"","wr":"","dd":"50.0000","deductible_0":"200.0000","deductible_50":"100.0000","deductible_100":"0.0000","deductible_250":""},

{"pricerId":"655475","rank":"655448","programCode":"NSE","programText":"New Vehicle - NSE","coverage":"Reserve","classRoom":"4",
"term":"60/75","planMonths":"60","planMiles":"75000","price":"1078.0000","awd":"","turbo":"","diesel":"","hv":"","buse":"250.0000",
"sg":"","wr":"","dd":"50.0000","deductible_0":"200.0000","deductible_50":"100.0000","deductible_100":"0.0000","deductible_250":""},

{"pricerId":"655481","rank":"655448","programCode":"NSE","programText":"New Vehicle - NSE","coverage":"Reserve","classRoom":"4",
"term":"60/100","planMonths":"60","planMiles":"100000","price":"1197.0000","awd":"","turbo":"","diesel":"","hv":"","buse":"250.0000",
"sg":"","wr":"","dd":"50.0000","deductible_0":"200.0000","deductible_50":"100.0000","deductible_100":"0.0000","deductible_250":""},

{"pricerId":"655487","rank":"655448","programCode":"NSE","programText":"New Vehicle - NSE","coverage":"Reserve","classRoom":"4",
"term":"60/125","planMonths":"60","planMiles":"125000","price":"1329.0000","awd":"","turbo":"","diesel":"","hv":"","buse":"250.0000",
"sg":"","wr":"","dd":"50.0000","deductible_0":"200.0000","deductible_50":"100.0000","deductible_100":"0.0000","deductible_250":""},

{"pricerId":"655493","rank":"655448","programCode":"NSE","programText":"New Vehicle - NSE","coverage":"Reserve","classRoom":"4",
"term":"72/60","planMonths":"72","planMiles":"60000","price":"1072.0000","awd":"","turbo":"","diesel":"","hv":"","buse":"250.0000",
"sg":"","wr":"","dd":"50.0000","deductible_0":"200.0000","deductible_50":"100.0000","deductible_100":"0.0000","deductible_250":""},

{"pricerId":"655499","rank":"655448","programCode":"NSE","programText":"New Vehicle - NSE","coverage":"Reserve","classRoom":"4",
"term":"72/75","planMonths":"72","planMiles":"75000","price":"1104.0000","awd":"","turbo":"","diesel":"","hv":"","buse":"250.0000",
"sg":"","wr":"","dd":"50.0000","deductible_0":"200.0000","deductible_50":"100.0000","deductible_100":"0.0000","deductible_250":""},

{"pricerId":"655505","rank":"655448","programCode":"NSE","programText":"New Vehicle - NSE","coverage":"Reserve","classRoom":"4",
"term":"72/100","planMonths":"72","planMiles":"100000","price":"1220.0000","awd":"","turbo":"","diesel":"","hv":"","buse":"250.0000",
"sg":"","wr":"","dd":"50.0000","deductible_0":"200.0000","deductible_50":"100.0000","deductible_100":"0.0000","deductible_250":""},

{"pricerId":"655511","rank":"655448","programCode":"NSE","programText":"New Vehicle - NSE","coverage":"Reserve","classRoom":"4",
"term":"72/125","planMonths":"72","planMiles":"125000","price":"1370.0000","awd":"","turbo":"","diesel":"","hv":"","buse":"250.0000",
"sg":"","wr":"","dd":"50.0000","deductible_0":"200.0000","deductible_50":"100.0000","deductible_100":"0.0000","deductible_250":""},

{"pricerId":"222756","rank":"222561","programCode":"SNF","programText":"Used Vehicle - SNF","coverage":"Estate","classRoom":"1",
"term":"36/36","planMonths":"36","planMiles":"36000","price":"915.0000","awd":"","turbo":"","diesel":"","hv":"","buse":"250.0000",
"sg":"0.0000","wr":"50.0000","dd":"100.0000","deductible_0":"150.0000","deductible_50":"","deductible_100":"0.0000","deductible_250":"-115.0000"},

{"pricerId":"222819","rank":"222561","programCode":"SNF","programText":"Used Vehicle - SNF","coverage":"Estate","classRoom":"1",
"term":"48/48","planMonths":"48","planMiles":"48000","price":"1050.0000","awd":"","turbo":"","diesel":"","hv":"","buse":"250.0000",
"sg":"0.0000","wr":"50.0000","dd":"100.0000","deductible_0":"150.0000","deductible_50":"","deductible_100":"0.0000","deductible_250":"-115.0000"}]}
